LICENSE
README.md
clickpiyush.py
setup.cfg
setup.py
clickpiyush.egg-info/PKG-INFO
clickpiyush.egg-info/SOURCES.txt
clickpiyush.egg-info/dependency_links.txt
clickpiyush.egg-info/entry_points.txt
clickpiyush.egg-info/requires.txt
clickpiyush.egg-info/top_level.txt